captur_ml_sdk/__init__.py
captur_ml_sdk/dtypes/__init__.py
captur_ml_sdk/dtypes/exceptions/__init__.py
captur_ml_sdk/dtypes/generics/Image.py
captur_ml_sdk/dtypes/generics/Meta.py
captur_ml_sdk/dtypes/generics/Model.py
captur_ml_sdk/dtypes/generics/__init__.py
captur_ml_sdk/dtypes/interfaces/__init__.py
captur_ml_sdk/dtypes/interfaces/validators.py
captur_ml_sdk/dtypes/interfaces/MLEval/EvalEventData.py
captur_ml_sdk/dtypes/interfaces/MLEval/__init__.py
captur_ml_sdk/dtypes/interfaces/MLGateway/MLEvalRequest.py
captur_ml_sdk/dtypes/interfaces/MLGateway/MLGatewayRequest.py
captur_ml_sdk/dtypes/interfaces/MLGateway/MLLivePredictRequest.py
captur_ml_sdk/dtypes/interfaces/MLGateway/MLMetaRequest.py
captur_ml_sdk/dtypes/interfaces/MLGateway/MLPredictRequest.py
captur_ml_sdk/dtypes/interfaces/MLGateway/MLRegisterModel.py
captur_ml_sdk/dtypes/interfaces/MLGateway/MLTrainRequest.py
captur_ml_sdk/dtypes/interfaces/MLGateway/__init__.py
captur_ml_sdk/dtypes/interfaces/MLLivePredict/LivePredictEventData.py
captur_ml_sdk/dtypes/interfaces/MLLivePredict/__init__.py
captur_ml_sdk/dtypes/interfaces/MLPredict/OfflinePostRunEventData.py
captur_ml_sdk/dtypes/interfaces/MLPredict/OfflinePreRunEventData.py
captur_ml_sdk/dtypes/interfaces/MLPredict/OfflineRunEventData.py
captur_ml_sdk/dtypes/interfaces/MLPredict/__init__.py
captur_ml_sdk/dtypes/interfaces/MLReg/RegisterModelEventData.py
captur_ml_sdk/dtypes/interfaces/MLReg/__init__.py
captur_ml_sdk/dtypes/interfaces/MLTrain/PreRunEventData.py
captur_ml_sdk/dtypes/interfaces/MLTrain/RunEventData.py
captur_ml_sdk/dtypes/interfaces/MLTrain/TrainingEvalEventData.py
captur_ml_sdk/dtypes/interfaces/MLTrain/__init__.py
captur_ml_sdk/utils/__init__.py
captur_ml_sdk/utils/gcp_functions.py
captur_ml_sdk/utils/get_image_components.py
captur_ml_sdk/utils/logging_functions.py
captur_ml_sdk-0.1.96.dist-info/LICENCE.md
captur_ml_sdk-0.1.96.dist-info/METADATA
captur_ml_sdk-0.1.96.dist-info/WHEEL
captur_ml_sdk-0.1.96.dist-info/top_level.txt
captur_ml_sdk-0.1.96.dist-info/RECORD
