Metadata-Version: 2.1
Name: captur-ml-sdk
Version: 0.1.96
Summary: The internal Captur Machine Learning SDK
Home-page: https://github.com/Captur/captur-ml-sdk
Author: ['Jack Barnett Leveson', 'Jonny Jackson']
Author-email: jack@capturphotos.com
License: Creative Commons Attribution-NonCommercial-NoDerivatives 4.0 International
Platform: UNKNOWN
Classifier: Intended Audience :: Developers
Classifier: License :: OSI Approved :: BSD License
Classifier: Operating System :: POSIX :: Linux
Classifier: Programming Language :: Python :: 3
Classifier: Programming Language :: Python :: 3.7
Classifier: Programming Language :: Python :: 3.8
Classifier: Programming Language :: Python :: 3.9
Requires-Python: >=3.7
Requires-Dist: pydantic
